README
setup.py
riakkit/__init__.py
riakkit/document.py
riakkit/helpers.py
riakkit/queries.py
riakkit.egg-info/PKG-INFO
riakkit.egg-info/SOURCES.txt
riakkit.egg-info/dependency_links.txt
riakkit.egg-info/requires.txt
riakkit.egg-info/top_level.txt
riakkit/commons/__init__.py
riakkit/commons/exceptions.py
riakkit/commons/properties.py
riakkit/simple/__init__.py
riakkit/simple/basedocument.py