Metadata-Version: 1.0
Name: riakkit
Version: 0.6.0a
Summary: An object mapper for Riak similar to mongokit and couchdbkit for Riak
Home-page: https://github.com/ultimatebuster/riakkit
Author: Shuhao Wu
Author-email: shuhao@shuhaowu.com
License: LGPL
Keywords: riak object mapper riakkit database orm
Platform: UNKNOWN
Classifier: Development Status :: 3 - Alpha
Classifier: License :: OSI Approved :: GNU Library or Lesser General Public License (LGPL)
Classifier: Intended Audience :: Developers
Classifier: Topic :: Database
Classifier: Topic :: Software Development :: Libraries :: Python Modules
